AUTHORS
CHANGELOG.rst
LICENSE
MANIFEST.in
README.rst
setup.py
xapian_backend.py
tests/xapian_settings.py
tests/xapian_tests/__init__.py
tests/xapian_tests/models.py
tests/xapian_tests/search_indexes.py
tests/xapian_tests/migrations/0001_initial.py
tests/xapian_tests/migrations/__init__.py
tests/xapian_tests/tests/__init__.py
tests/xapian_tests/tests/test_backend.py
tests/xapian_tests/tests/test_interface.py
tests/xapian_tests/tests/test_management_commands.py
tests/xapian_tests/tests/test_query.py
yapian_haystack.egg-info/PKG-INFO
yapian_haystack.egg-info/SOURCES.txt
yapian_haystack.egg-info/dependency_links.txt
yapian_haystack.egg-info/requires.txt
yapian_haystack.egg-info/top_level.txt