Metadata-Version: 2.1
Name: yapian-haystack
Version: 3.1.0
Summary: A Xapian backend for Haystack
Home-page: https://github.com/notanumber/xapian-haystack
Author: Jorge C. Leitão
Author-email: jorgecarleitao@gmail.com
License: GPL2
Classifier: Development Status :: 5 - Production/Stable
Classifier: Intended Audience :: Developers
Classifier: License :: OSI Approved :: GNU General Public License (GPL)
Classifier: Topic :: Internet :: WWW/HTTP :: Indexing/Search
Classifier: Framework :: Django
Classifier: Programming Language :: Python :: 3 :: Only
License-File: LICENSE
License-File: AUTHORS
